CHANGELOG.md
isobar_ext/__init__.py
isobar_ext/chord.py
isobar_ext/constants.py
isobar_ext/exceptions.py
isobar_ext/io/__init__.py
isobar_ext/io/cv/__init__.py
isobar_ext/io/cv/output.py
isobar_ext/io/dummy/__init__.py
isobar_ext/io/dummy/output.py
isobar_ext/io/midi/__init__.py
isobar_ext/io/midi/input.py
isobar_ext/io/midi/output.py
isobar_ext/io/midifile/__init__.py
isobar_ext/io/midifile/input.py
isobar_ext/io/midifile/output.py
isobar_ext/io/midimessages.py
isobar_ext/io/midinote.py
isobar_ext/io/netclock/__init__.py
isobar_ext/io/netclock/receiver.py
isobar_ext/io/netclock/sender.py
isobar_ext/io/netglobals/__init__.py
isobar_ext/io/netglobals/receiver.py
isobar_ext/io/netglobals/sender.py
isobar_ext/io/osc/__init__.py
isobar_ext/io/osc/output.py
isobar_ext/io/output.py
isobar_ext/io/signalflow/__init__.py
isobar_ext/io/signalflow/output.py
isobar_ext/io/socketio/__init__.py
isobar_ext/io/socketio/output.py
isobar_ext/io/supercollider/__init__.py
isobar_ext/io/supercollider/output.py
isobar_ext/key.py
isobar_ext/notation/__init__.py
isobar_ext/notation/notation.py
isobar_ext/note.py
isobar_ext/pattern/__init__.py
isobar_ext/pattern/chance.py
isobar_ext/pattern/core.py
isobar_ext/pattern/fade.py
isobar_ext/pattern/lsystem.py
isobar_ext/pattern/markov.py
isobar_ext/pattern/midi.py
isobar_ext/pattern/oscillator.py
isobar_ext/pattern/scalar.py
isobar_ext/pattern/sequence.py
isobar_ext/pattern/series.py
isobar_ext/pattern/static.py
isobar_ext/pattern/tonal.py
isobar_ext/pattern/warp.py
isobar_ext/scale.py
isobar_ext/scales.json
isobar_ext/shorthand/__init__.py
isobar_ext/shorthand/abbreviations.py
isobar_ext/shorthand/patches.py
isobar_ext/shorthand/setup.py
isobar_ext/shorthand/sync.py
isobar_ext/timelines/__init__.py
isobar_ext/timelines/clock.py
isobar_ext/timelines/clock_link.py
isobar_ext/timelines/event.py
isobar_ext/timelines/timeline.py
isobar_ext/timelines/track.py
isobar_ext/util.py
isobar_ext-0.9.0.dist-info/LICENSE.md
isobar_ext-0.9.0.dist-info/METADATA
isobar_ext-0.9.0.dist-info/WHEEL
isobar_ext-0.9.0.dist-info/RECORD
