Metadata-Version: 2.1
Name: isobar_ext
Version: 0.9.0
Summary: A Python library to express and manipulate musical patterns extending the original isobar library.
Home-page: https://github.com/piotereks/isobar-ext
License: MIT
Keywords: sound,music,composition
Author: Piotr Sakowski
Author-email: piotereks@gmail.com
Requires-Python: >=3.9,<4.0
Classifier: Development Status :: 4 - Beta
Classifier: Intended Audience :: Developers
Classifier: License :: OSI Approved :: MIT License
Classifier: Programming Language :: Python :: 3
Classifier: Programming Language :: Python :: 3.9
Classifier: Programming Language :: Python :: 3.10
Classifier: Programming Language :: Python :: 3.11
Classifier: Programming Language :: Python :: 3.12
Classifier: Topic :: Artistic Software
Classifier: Topic :: Multimedia :: Sound/Audio
Requires-Dist: mido
Requires-Dist: python-osc
Requires-Dist: python-rtmidi
Project-URL: Documentation, http://piotereks.github.io/isobar-ext
Project-URL: Repository, https://github.com/piotereks/isobar-ext
